LICENSE.txt
README.md
setup.cfg
setup.py
countdowntimer/__init__.py
countdowntimer/countdown.py
pycountdown.egg-info/PKG-INFO
pycountdown.egg-info/SOURCES.txt
pycountdown.egg-info/dependency_links.txt
pycountdown.egg-info/entry_points.txt
pycountdown.egg-info/top_level.txt